graphwar/__init__.py
graphwar/surrogate.py
graphwar/version.py
graphwar/attack/__init__.py
graphwar/attack/attacker.py
graphwar/attack/flip_attacker.py
graphwar/attack/backdoor/__init__.py
graphwar/attack/backdoor/backdoor_attacker.py
graphwar/attack/backdoor/lgc_backdoor.py
graphwar/attack/injection/__init__.py
graphwar/attack/injection/adv_injection.py
graphwar/attack/injection/injection_attacker.py
graphwar/attack/injection/random_injection.py
graphwar/attack/targeted/__init__.py
graphwar/attack/targeted/dice_attack.py
graphwar/attack/targeted/fg_attack.py
graphwar/attack/targeted/gf_attack.py
graphwar/attack/targeted/ig_attack.py
graphwar/attack/targeted/nettack.py
graphwar/attack/targeted/random_attack.py
graphwar/attack/targeted/sg_attack.py
graphwar/attack/targeted/targeted_attacker.py
graphwar/attack/untargeted/__init__.py
graphwar/attack/untargeted/dice_attack.py
graphwar/attack/untargeted/fg_attack.py
graphwar/attack/untargeted/ig_attack.py
graphwar/attack/untargeted/metattack.py
graphwar/attack/untargeted/pgd_attack.py
graphwar/attack/untargeted/random_attack.py
graphwar/attack/untargeted/untargeted_attacker.py
graphwar/dataset/__init__.py
graphwar/dataset/graphwar_dataset.py
graphwar/defense/__init__.py
graphwar/defense/gnnguard.py
graphwar/defense/purification.py
graphwar/defense/universal_defense.py
graphwar/functional/__init__.py
graphwar/functional/dropouts.py
graphwar/functional/spmm.py
graphwar/functional/transform.py
graphwar/nn/__init__.py
graphwar/nn/layers/__init__.py
graphwar/nn/layers/activations.py
graphwar/nn/layers/adaptive_conv.py
graphwar/nn/layers/container.py
graphwar/nn/layers/dagnn_conv.py
graphwar/nn/layers/dropouts.py
graphwar/nn/layers/elastic_conv.py
graphwar/nn/layers/gcn_conv.py
graphwar/nn/layers/median_conv.py
graphwar/nn/layers/robust_conv.py
graphwar/nn/layers/sat_conv.py
graphwar/nn/layers/sg_conv.py
graphwar/nn/layers/soft_median_conv.py
graphwar/nn/layers/ssg_conv.py
graphwar/nn/layers/tag_conv.py
graphwar-0.1.0.dist-info/LICENSE
graphwar-0.1.0.dist-info/METADATA
graphwar-0.1.0.dist-info/WHEEL
graphwar-0.1.0.dist-info/top_level.txt
graphwar-0.1.0.dist-info/RECORD
